liquidctl/__init__.py
liquidctl/__main__.py
liquidctl/_version.py
liquidctl/cli.py
liquidctl/error.py
liquidctl/keyval.py
liquidctl/pmbus.py
liquidctl/util.py
liquidctl/version.py
liquidctl/driver/__init__.py
liquidctl/driver/aquacomputer.py
liquidctl/driver/asetek.py
liquidctl/driver/asetek_pro.py
liquidctl/driver/asus_ryujin.py
liquidctl/driver/aura_led.py
liquidctl/driver/base.py
liquidctl/driver/commander_core.py
liquidctl/driver/commander_pro.py
liquidctl/driver/coolit.py
liquidctl/driver/corsair_hid_psu.py
liquidctl/driver/ddr4.py
liquidctl/driver/hwmon.py
liquidctl/driver/hydro_platinum.py
liquidctl/driver/kraken2.py
liquidctl/driver/kraken3.py
liquidctl/driver/msi.py
liquidctl/driver/nvidia.py
liquidctl/driver/nzxt_epsu.py
liquidctl/driver/rgb_fusion2.py
liquidctl/driver/smart_device.py
liquidctl/driver/smbus.py
liquidctl/driver/usb.py
liquidctl-1.15.0.dist-info/licenses/LICENSE.txt
liquidctl-1.15.0.dist-info/METADATA
liquidctl-1.15.0.dist-info/WHEEL
liquidctl-1.15.0.dist-info/entry_points.txt
liquidctl-1.15.0.dist-info/top_level.txt
liquidctl-1.15.0.dist-info/RECORD
