Metadata-Version: 2.4
Name: liquidctl
Version: 1.15.0
Summary: Cross-platform tool and drivers for liquid coolers and other devices
Home-page: https://github.com/liquidctl/liquidctl
Author: Jonas Malaco
Author-email: jonas@protocubo.io
Project-URL: Documentation, https://github.com/liquidctl/liquidctl/blob/main/README.md
Project-URL: Changelog, https://github.com/liquidctl/liquidctl/blob/main/CHANGELOG.md
Project-URL: Source, https://github.com/liquidctl/liquidctl
Keywords: aio,aquacomputer,asus,clc,cli,corsair,cross-platform,dram,driver,evga,fan-controller,gigabyte,hue2,kraken,led-controller,liquid-cooler,nzxt,power-supply,smart-device
Classifier: Development Status :: 5 - Production/Stable
Classifier: Intended Audience :: Developers
Classifier: Intended Audience :: End Users/Desktop
Classifier: License :: OSI Approved :: GNU General Public License v3 or later (GPLv3+)
Classifier: Operating System :: OS Independent
Classifier: Programming Language :: Python :: 3.13
Classifier: Programming Language :: Python :: 3.12
Classifier: Programming Language :: Python :: 3.11
Classifier: Programming Language :: Python :: 3.10
Classifier: Programming Language :: Python :: 3.9
Classifier: Topic :: System :: Hardware :: Hardware Drivers
Requires-Python: >=3.9
License-File: LICENSE.txt
Requires-Dist: colorlog
Requires-Dist: crcmod==1.7
Requires-Dist: docopt
Requires-Dist: hidapi
Requires-Dist: pyusb
Requires-Dist: pillow
Requires-Dist: libusb-package; sys_platform == "win32" or sys_platform == "cygwin"
Requires-Dist: winusbcdc>=1.5; sys_platform == "win32"
Requires-Dist: smbus; sys_platform == "linux"
Dynamic: license-file
